{"id":"21032","skill":"Secret","desc":"L'un des effets suivants s'applique aléatoirement en début de combat et à chaque fois que le tour du porteur commence : l'ATQ de tous les alliés augmente de #1[i]%, les DGT critiques de tous les alliés augmentent de #2[i]% ou le taux de régénération d'énergie de tous les alliés augmente de #3[i]%. L'effet appliqué ne peut pas être identique au précédent et le remplace. L'effet appliqué est supprimé lorsque le porteur est à terre. Les effets du même type ne se cumulent pas.","params":[[0.1,0.12,0.06],[0.125,0.15,0.075],[0.15,0.18,0.09],[0.175,0.21,0.105],[0.2,0.24,0.12]],"properties":[[],[],[],[],[]]}