{"id":"1401101","name":"Равнодушная честность","max_level":1,"desc":"Атаки союзников накладывают на поражённых противников 1 ур. статуса Интерпретация. После атаки Великая Герта восстанавливает #1[i] ед. энергии за каждого поражённого этой атакой противника до макс. 5 целей. Если при использовании усиленного навыка количество уровней имеющегося у основной цели статуса Интерпретация достигает 42, то наносимый Великой Гертой урон повышается на #2[i]% до окончания текущей атаки.","params":[[3,0.5]],"anchor":"Point06","pre_points":[],"level_up_skills":[],"levels":[{"promotion":2,"level":0,"properties":[],"materials":[{"id":"2","num":5000},{"id":"110201","num":3},{"id":"110506","num":1}]}],"icon":"icon/skill/1401_skilltree1.png"}