{"id":"1003101","name":"Starfire","max_level":1,"desc":"After using an attack, there is a #1[i]% base chance to inflict Burn on enemies, lasting for #2[i] turn(s).\nWhen afflicted with Burn, enemies take Fire DoT equal to #3[i]% of Himeko's ATK at the start of each turn.","params":[[0.5,2,0.3]],"anchor":"Point06","pre_points":[],"level_up_skills":[],"levels":[{"promotion":2,"level":0,"properties":[],"materials":[{"id":"2","num":5000},{"id":"110131","num":3},{"id":"110501","num":1}]}],"icon":"icon/skill/1003_skilltree1.png"}