{"id":"302","name":"O Preço da Paz","desc":"Recebe 150 Fragmentos Cósmicos ao entrar em um Domínio de Transação.","bg_desc":"O Grupo de Apoio à Majestade Âmbar se expandiu rapidamente nos anos após o Desastre do Enxame, se estabelecendo como a Corporação da Paz Interastral, florescendo a alturas inalcançáveis. Porém, afetada pela Guerra Comercial da Fronteira Estelar e pela Guerra do Imperador, o caminho da organização em direção à paz interastral se tornou cada vez mais árduo. Depois de mais dez Eras de Âmbar, essa guerra acabou com a queda do Império Maquinário. O universo deu finalmente as boas-vindas à \"Segunda Prosperidade\", que viria a durar por centenas de Eras de Âmbar. As pessoas acreditavam que esta era de prosperidade nunca acabaria, até o dia em que a ainda mais terrível Guerra de Energia Interestelar teve seu início.","icon":"icon/curio/1074.png"}