{"id":"120703","name":"Ныряющий ястреб","max_level":15,"element":"Imaginary","type":"Ultra","type_text":"Сверхспособность","effect":"SingleAttack","effect_text":"Одиночная атака","simple_desc":"Когда активен статус Ревущая тетива, крит. шанс и крит. урон от всех союзников повышается. Персонаж также наносит огромный мнимый урон выбранному противнику.","desc":"Использование сверхспособности Юйкун при активном статусе Ревущая тетива дополнительно повышает крит. шанс всех союзников на #2[i]% и их крит. урон на #3[i]%, а также наносит выбранному противнику мнимый урон, равный #1[i]% от силы атаки Юйкун.","params":[[2.28,0.21,0.39],[2.432,0.217,0.416],[2.584,0.224,0.442],[2.736,0.231,0.468],[2.888,0.238,0.494],[3.04,0.245,0.52],[3.23,0.2538,0.5525],[3.42,0.2625,0.585],[3.61,0.2713,0.6175],[3.8,0.28,0.65],[3.952,0.287,0.676],[4.104,0.294,0.702],[4.256,0.301,0.728],[4.408,0.308,0.754],[4.56,0.315,0.78]],"icon":"icon/skill/1207_ultimate.png"}