{"id":"22003","skill":"Vorhang auf!","desc":"Erhöht die max. LP des Trägers um #1[i]%. Nachdem der Träger LP verloren oder wiederhergestellt hat, wird sein KRIT-SCH für #3[i] Rd. um #2[i]% erhöht. Dieser Effekt kann nur 1-mal pro Runde ausgelöst werden.","params":[[0.12,0.18,2],[0.15,0.225,2],[0.18,0.27,2],[0.21,0.315,2],[0.24,0.36,2]],"properties":[[{"type":"HPAddedRatio","value":0.12}],[{"type":"HPAddedRatio","value":0.15}],[{"type":"HPAddedRatio","value":0.18}],[{"type":"HPAddedRatio","value":0.21}],[{"type":"HPAddedRatio","value":0.24}]]}