{"id":"23010","name":"Before Dawn","rarity":5,"path":"Mage","desc":"\"ท่านนายพล โปรดตระหนักให้ดีด้วยว่า... ประวัติศาสตร์ข้างหน้าจะจดจำท่านไว้อย่างไร...\"\nนายพลแห่ง Cloud Knight หลับตาลง และฟังการรายงานจากลูกน้องของเขา\n\"ประวัติศาสตร์จะต้องตัดสินอยู่แล้ว แต่ฉันไม่สนใจหรอกว่าประวัติศาสตร์จะบันทึกเรื่องของฉันไว้แบบไหน\"\n\"หากทำสำเร็จ ตอนนี้ฉันคงจะเป็นคนที่วางแผนได้รอบคอบถี่ถ้วน และมีชีวิตสงบสุข\"\n\"แต่ถ้าหากล้มเหลว ตอนนี้ฉันคงจะเป็นพวกรักความสบาย เข้าข้างแต่ฝ่ายตัวเอง\"\nนกน้อยกระโดดลงจากไหล่ของเขามาอยู่บนฝ่ามือ\n\"ฉันก็แค่ทำสิ่งที่ตัดสินใจเอาไว้แล้วก็เท่านั้น\"","icon":"icon/light_cone/23010.png","preview":"image/light_cone_preview/23010.png","portrait":"image/light_cone_portrait/23010.png"}