{"id":"23015","skill":"この命に替えても","desc":"装備キャラの会心率+#1[i]%。装備キャラが通常攻撃を行った時、「龍吟」を1層獲得する、#2[i]ターン継続。「龍吟」1層につき、装備キャラの攻撃力+#4[i]%、EP回復効率+#5[f1]%。「龍吟」は最大で#3[i]層累積できる。","params":[[0.18,2,2,0.18,0.06],[0.21,2,2,0.21,0.07],[0.24,2,2,0.24,0.08],[0.27,2,2,0.27,0.09],[0.3,2,2,0.3,0.1]],"properties":[[{"type":"CriticalChanceBase","value":0.18}],[{"type":"CriticalChanceBase","value":0.21}],[{"type":"CriticalChanceBase","value":0.24}],[{"type":"CriticalChanceBase","value":0.27}],[{"type":"CriticalChanceBase","value":0.3}]]}