{"id":"23043","name":"谎言在风中飘扬","rarity":5,"path":"Warlock","desc":"猫耳少女于屋顶舒展身姿，滑入夜色。\n于那沉寂千年的宝库，少女轻盈地穿梭，将珍宝纳入怀中，又无声无息地逃离。\n「愚蠢的命运，可追不上我！」\n废墟中的风裹挟着荒野的味道，吹动少女的兜帽。\n枕着冰凉的石块，她咽下粗粝的干粮，抛逗着指尖的金币。\n远方细微的声响落入她的双耳，在那黎明照耀的圣城，熙熙攘攘的人群仍在享受欢宴与温暖。\n「还有多久…一年，还是一万年？」\n她伸个懒腰，将不安的思绪抛在身后。\n「呵，赛法利娅总会笑到最后！」\n金色的闪电划过天空，少女的宣言仍在风中飘扬\n——一如千年前的模样。","icon":"icon/light_cone/23043.png","preview":"image/light_cone_preview/23043.png","portrait":"image/light_cone_portrait/23043.png","ranks":{"id":"23043","skill":"欺瞒","desc":"使装备者的速度提高#1[i]%。装备者施放攻击后，有#2[i]%的基础概率使敌方每个单体目标陷入【茫然】状态，【茫然】状态下的敌方目标防御力降低#3[i]%，持续#4[i]回合，若装备者的速度大于等于#7[i]，有#5[i]%的基础概率使敌方每个单体目标陷入【失窃】状态，【失窃】状态下的敌方目标防御力降低#6[i]%，持续#4[i]回合。【茫然】或【失窃】被重复施加时，仅最新施加的生效。","params":[[0.18,1.2,0.16,2,1.2,0.08,170],[0.21,1.2,0.18,2,1.2,0.09,170],[0.24,1.2,0.2,2,1.2,0.1,170],[0.27,1.2,0.22,2,1.2,0.11,170],[0.3,1.2,0.24,2,1.2,0.12,170]],"properties":[[{"type":"SpeedAddedRatio","value":0.18}],[{"type":"SpeedAddedRatio","value":0.21}],[{"type":"SpeedAddedRatio","value":0.24}],[{"type":"SpeedAddedRatio","value":0.27}],[{"type":"SpeedAddedRatio","value":0.3}]]},"promotions":{"id":"23043","values":[{"hp":{"base":43.2,"step":6.48},"atk":{"base":26.4,"step":3.96},"def":{"base":24,"step":3.6}},{"hp":{"base":95.04,"step":6.48},"atk":{"base":58.08,"step":3.96},"def":{"base":52.8,"step":3.6}},{"hp":{"base":164.16,"step":6.48},"atk":{"base":100.32,"step":3.96},"def":{"base":91.2,"step":3.6}},{"hp":{"base":233.28,"step":6.48},"atk":{"base":142.56,"step":3.96},"def":{"base":129.6,"step":3.6}},{"hp":{"base":302.4,"step":6.48},"atk":{"base":184.8,"step":3.96},"def":{"base":168,"step":3.6}},{"hp":{"base":371.52,"step":6.48},"atk":{"base":227.04,"step":3.96},"def":{"base":206.4,"step":3.6}},{"hp":{"base":440.64,"step":6.48},"atk":{"base":269.28,"step":3.96},"def":{"base":244.8,"step":3.6}}],"materials":[[{"id":"2","num":5000},{"id":"115011","num":8}],[{"id":"2","num":10000},{"id":"110221","num":4},{"id":"115011","num":12}],[{"id":"2","num":20000},{"id":"110222","num":4},{"id":"115012","num":8}],[{"id":"2","num":50000},{"id":"110222","num":8},{"id":"115012","num":12}],[{"id":"2","num":100000},{"id":"110223","num":5},{"id":"115013","num":6}],[{"id":"2","num":200000},{"id":"110223","num":10},{"id":"115013","num":8}],[]]}}