{"id":"100202","name":"Thương Thuật Vân Kỵ - Lũ Cuốn","max_level":15,"element":"Wind","type":"BPSkill","type_text":"Chiến Kỹ","effect":"SingleAttack","effect_text":"Đánh Đơn","simple_desc":"Gây Sát Thương Phong cho 1 kẻ địch, khi bạo kích có xác suất lớn thi triển trạng thái Giảm Tốc.","desc":"Gây Sát Thương Phong cho 1 kẻ địch chỉ định tương đương #1[i]% Tấn Công của Dan Heng.\nKhi Chiến Kỹ gây sát thương kích hoạt bạo kích, có #4[i]% xác suất cơ bản khiến mục tiêu phe địch bị tấn công giảm tốc #2[i]%, duy trì #3[i] hiệp.","params":[[1.3,0.12,2,1],[1.43,0.12,2,1],[1.56,0.12,2,1],[1.69,0.12,2,1],[1.82,0.12,2,1],[1.95,0.12,2,1],[2.1125,0.12,2,1],[2.275,0.12,2,1],[2.4375,0.12,2,1],[2.6,0.12,2,1],[2.73,0.12,2,1],[2.86,0.12,2,1],[2.99,0.12,2,1],[3.12,0.12,2,1],[3.25,0.12,2,1]],"icon":"icon/skill/1002_skill.png"}