{"id":"120302","name":"Tịnh Đình Tặng Lễ","rank":2,"desc":"Khi kích hoạt hiệu ứng Chiến Kỹ, nếu phần trăm HP hiện tại của mục tiêu chỉ định của phe ta dưới 50%, thì lượng trị liệu mà Luocha cung cấp sẽ tăng 30%; nếu phần trăm HP hiện tại của mục tiêu chỉ định của phe ta từ 50% trở lên, sẽ cung cấp cho mục tiêu đó một tấm Khiên có thể triệt tiêu sát thương bằng 18% Tấn Công của Luocha +240, duy trì 2 hiệp.","materials":[{"id":"11203","num":1}],"level_up_skills":[],"icon":"icon/skill/1203_rank2.png"}