{"id":"1305101","name":"Summation","max_level":1,"desc":"Saat melancarkan Skill, untuk setiap 1 efek Debuff yang dimiliki target, CRIT Rate Dr. Ratio akan meningkat #1[f1]%, dan CRIT DMG meningkat #2[i]%. Efek ini dapat ditumpuk hingga #3[i] lapis.","params":[[0.025,0.05,6]],"anchor":"Point06","pre_points":[],"level_up_skills":[],"levels":[{"promotion":2,"level":0,"properties":[],"materials":[{"id":"2","num":5000},{"id":"110121","num":3},{"id":"110504","num":1}]}],"icon":"icon/skill/1305_skilltree1.png"}