{"id":"110307","name":"Buenas noches, Belobog","max_level":1,"element":"Thunder","type":"Maze","type_text":"Técnica","effect":"MazeAttack","effect_text":"","simple_desc":"Ataca al enemigo y entra en combate. Inflige una pequeña cantidad de daño a un enemigo al azar. Además, cada enemigo tiene una gran probabilidad de ser afectado por Electrocución.","desc":"Ataca inmediatamente al enemigo y entra en combate. Inflige un #4[i]% del ATQ de Serval como Daño de Rayo a un enemigo al azar. Además, cada enemigo tiene una probabilidad base del #1[i]% de ser afectado por Electrocución durante #3[i] turnos.\nLos enemigos electrocutados reciben un Daño de Rayo con el tiempo equivalente al #2[i]% del ATQ de Serval al comienzo de cada turno.","params":[[1,0.5,3,0.5]],"icon":"icon/skill/1103_technique.png"}