{"id":"130703","name":"沉醉於彼界的臂灣","max_level":15,"element":"Wind","type":"Ultra","type_text":"終結技","effect":"AoEAttack","effect_text":"群體攻擊","simple_desc":"對敵方全體施加【揭露】狀態，使目標回合內受到的傷害提高，並將【奧跡】視為風化、裂傷、灼燒、觸電狀態，此外使【奧跡】下一次回合開始造成傷害後不重置層數。對敵方全體造成風屬性傷害。","desc":"使敵方全體陷入【揭露】狀態，持續#2[i]回合。\n【揭露】狀態下，敵方目標自身回合內受到的傷害提高#3[i]%，且當敵方目標處於【奧跡】狀態時，也會視為同時陷入了風化、裂傷、灼燒、觸電狀態，並且【奧跡】每回合開始造成傷害後不會重置層數。【奧跡】不會重置層數的效果在【揭露】狀態持續時間內最多觸發#4[i]次，再次陷入【揭露】狀態會刷新觸發次數。\n對敵方全體造成等同於黑天鵝#1[i]%攻擊力的風屬性傷害。","params":[[0.72,2,0.15,1],[0.768,2,0.16,1],[0.816,2,0.17,1],[0.864,2,0.18,1],[0.912,2,0.19,1],[0.96,2,0.2,1],[1.02,2,0.2125,1],[1.08,2,0.225,1],[1.14,2,0.2375,1],[1.2,2,0.25,1],[1.248,2,0.26,1],[1.296,2,0.27,1],[1.344,2,0.28,1],[1.392,2,0.29,1],[1.44,2,0.3,1]],"icon":"icon/skill/1307_ultimate.png"}