{"id":"23050","name":"彼女の炎を忘れずに","rarity":5,"path":"Warlock","desc":"「さあ、こちらへ……」\n炎に導かれた鮮やかな記憶が、彼女の身体と心を包み込む。\n過去が墓へと沈んでいく。それは真実なのだろうか？\n「しーっ、泣かないでください。拒まないでください……」\n彼女が他人の心に自分を刻みつけると、見知らぬ眼差しが次第に優しくなっていく。\n「思い出しましたか？」\n古い記憶の余燼が消え去り、その顔から人を魅了する花の香りがふわりと漂った——\n「私が、あなたの記憶なのです」","icon":"icon/light_cone/23050.png","preview":"image/light_cone_preview/23050.png","portrait":"image/light_cone_portrait/23050.png","ranks":{"id":"23050","skill":"燃える身","desc":"装備キャラの撃破特効+#1[i]%。戦闘に入る時、装備キャラの弱点撃破ダメージ+#2[i]%。\n装備キャラ以外の味方が戦闘を開始した場合、その味方の弱点撃破ダメージ+#2[i]%。なお、装備キャラが戦闘を開始またはその他の方法で戦闘に入った場合、装備キャラ以外で最も撃破特効の高い味方の弱点撃破ダメージ+#2[i]%。同系統のスキルは累積できない。\n装備キャラが敵に弱点を付与した時、SPを1回復する。この効果は1回まで発動でき、必殺技を発動するたびに、発動可能回数がリセットされる。","params":[[0.6,0.32],[0.75,0.42],[0.9,0.52],[1.05,0.62],[1.2,0.72]],"properties":[[{"type":"BreakDamageAddedRatioBase","value":0.6}],[{"type":"BreakDamageAddedRatioBase","value":0.75}],[{"type":"BreakDamageAddedRatioBase","value":0.9}],[{"type":"BreakDamageAddedRatioBase","value":1.05}],[{"type":"BreakDamageAddedRatioBase","value":1.2}]]},"promotions":{"id":"23050","values":[{"hp":{"base":52.8,"step":7.92},"atk":{"base":24,"step":3.6},"def":{"base":21,"step":3.15}},{"hp":{"base":116.16,"step":7.92},"atk":{"base":52.8,"step":3.6},"def":{"base":46.2,"step":3.15}},{"hp":{"base":200.64,"step":7.92},"atk":{"base":91.2,"step":3.6},"def":{"base":79.8,"step":3.15}},{"hp":{"base":285.12,"step":7.92},"atk":{"base":129.6,"step":3.6},"def":{"base":113.4,"step":3.15}},{"hp":{"base":369.6,"step":7.92},"atk":{"base":168,"step":3.6},"def":{"base":147,"step":3.15}},{"hp":{"base":454.08,"step":7.92},"atk":{"base":206.4,"step":3.6},"def":{"base":180.6,"step":3.15}},{"hp":{"base":538.56,"step":7.92},"atk":{"base":244.8,"step":3.6},"def":{"base":214.2,"step":3.15}}],"materials":[[{"id":"2","num":5000},{"id":"114011","num":8}],[{"id":"2","num":10000},{"id":"110221","num":4},{"id":"114011","num":12}],[{"id":"2","num":20000},{"id":"110222","num":4},{"id":"114012","num":8}],[{"id":"2","num":50000},{"id":"110222","num":8},{"id":"114012","num":12}],[{"id":"2","num":100000},{"id":"110223","num":5},{"id":"114013","num":6}],[{"id":"2","num":200000},{"id":"110223","num":10},{"id":"114013","num":8}],[]]}}