{"id":"131407","name":"Visionary Predation","max_level":1,"element":"","type":"Maze","type_text":"Technique","effect":"Impair","effect_text":"Impair","simple_desc":"Membuat musuh di dalam jangkauan tertentu memasuki status \"Blind Fealty\". Menyerang musuh yang berstatus \"Blind Fealty\" dapat membuat semua musuh yang berstatus \"Blind Fealty\" memasuki pertempuran secara bersamaan. Setelah memasuki pertempuran, mengakibatkan Quantum DMG dalam jumlah kecil pada seluruh musuh, dan Jade akan segera memperoleh 15 lapis \"Pawned Asset\".","desc":"Setelah menggunakan Technique, akan membuat musuh di dalam jangkauan tertentu memasuki status \"Blind Fealty\" selama #1[i] detik. Musuh yang berstatus \"Blind Fealty\" tidak akan secara aktif menyerang rekan tim. Saat secara aktif menyerang musuh yang berstatus \"Blind Fealty\" untuk memasuki pertempuran, akan membuat semua musuh yang berstatus \"Blind Fealty\" memasuki pertempuran secara bersamaan. Setelah memasuki pertempuran, mengakibatkan Quantum DMG sebesar #2[i]% ATK Jade pada seluruh musuh, dan Jade akan segera memperoleh #3[i] lapis \"Pawned Asset\".","params":[[10,0.5,15]],"icon":"icon/skill/1314_technique.png"}