{"id":"1800707","name":"Lemme! Help You!","max_level":10,"element":"","type":"MemospriteSkill","type_text":"Skill Memosprite","effect":"Support","effect_text":"Support","simple_desc":"Membuat 1 rekan tim mengalami Pendahuluan Aksi dan menambahkan \"Mem's Support\": Setelah mengakibatkan DMG, akan mengakibatkan tambahan True DMG.","desc":"Membuat 1 rekan tim yang ditargetkan mengalami Pendahuluan Aksi sebesar #3[i]% dan menambahkan \"Mem's Support\" selama #2[i] giliran.\nSetiap kali target yang memiliki \"Mem's Support\" mengakibatkan 1 kali DMG, akan mengakibatkan tambahan 1 kali True DMG sebesar #1[i]% dari DMG aslinya.\nSaat melancarkan kemampuan ini pada diri sendiri, efek Pendahuluan Aksi tidak dapat dipicu.","params":[[0.18,3,1],[0.2,3,1],[0.22,3,1],[0.24,3,1],[0.26,3,1],[0.28,3,1],[0.3,3,1],[0.32,3,1],[0.34,3,1],[0.36,3,1]],"icon":"icon/skill/8007_memosprite_skill.png"}