{"id":"21031","name":"또다시 저승으로","rarity":4,"path":"Rogue","desc":"언니의 곁에 있지만 그녀는 아무것도 들을 수 없었다.\n마음속의 소리만이 점점 더 커져 갔다.\n「언니의 몸이 차가워」\n「언니의 몸이 안 움직여」\n분노가 파도처럼 밀려와 그녀를 잠기게 했다. 그녀는 이미 생각할 겨를이 없었다——\n「언니의 몸은, 이미 오래전에 차가워졌어」","icon":"icon/light_cone/21031.png","preview":"image/light_cone_preview/21031.png","portrait":"image/light_cone_portrait/21031.png","ranks":{"id":"21031","skill":"용솟음","desc":"장착한 캐릭터의 치명타 확률이 #1[i]% 증가한다. 치명타 발동 후 #2[i]%의 고정 확률로 피격된 적이 보유한 버프 효과를 1개 해제한다. 해당 효과는 턴마다 1회만 발동할 수 있다","params":[[0.12,0.16],[0.15,0.2],[0.18,0.24],[0.21,0.28],[0.24,0.32]],"properties":[[{"type":"CriticalChanceBase","value":0.12}],[{"type":"CriticalChanceBase","value":0.15}],[{"type":"CriticalChanceBase","value":0.18}],[{"type":"CriticalChanceBase","value":0.21}],[{"type":"CriticalChanceBase","value":0.24}]]},"promotions":{"id":"21031","values":[{"hp":{"base":38.4,"step":5.76},"atk":{"base":24,"step":3.6},"def":{"base":15,"step":2.25}},{"hp":{"base":84.48,"step":5.76},"atk":{"base":52.8,"step":3.6},"def":{"base":33,"step":2.25}},{"hp":{"base":145.92,"step":5.76},"atk":{"base":91.2,"step":3.6},"def":{"base":57,"step":2.25}},{"hp":{"base":207.36,"step":5.76},"atk":{"base":129.6,"step":3.6},"def":{"base":81,"step":2.25}},{"hp":{"base":268.8,"step":5.76},"atk":{"base":168,"step":3.6},"def":{"base":105,"step":2.25}},{"hp":{"base":330.24,"step":5.76},"atk":{"base":206.4,"step":3.6},"def":{"base":129,"step":2.25}},{"hp":{"base":391.68,"step":5.76},"atk":{"base":244.8,"step":3.6},"def":{"base":153,"step":2.25}}],"materials":[[{"id":"2","num":4000},{"id":"113001","num":5}],[{"id":"2","num":8000},{"id":"110121","num":3},{"id":"113001","num":10}],[{"id":"2","num":16000},{"id":"110122","num":3},{"id":"113002","num":6}],[{"id":"2","num":40000},{"id":"110122","num":6},{"id":"113002","num":9}],[{"id":"2","num":80000},{"id":"110123","num":4},{"id":"113003","num":5}],[{"id":"2","num":160000},{"id":"110123","num":8},{"id":"113003","num":7}],[]]}}