{"id":"23018","skill":"Паломничество рыцаря","desc":"Крит. урон владельца повышается на #1[i]%. Когда владелец использует сверхспособность, наносимый ею урон повышается на #2[f2]% за каждую единицу от макс. энергии владельца. Этот эффект может складываться до макс. #3[i] ед. энергии.","params":[[0.36,0.0036,180],[0.42,0.0042,180],[0.48,0.0048,180],[0.54,0.0054,180],[0.6,0.006,180]],"properties":[[{"type":"CriticalDamageBase","value":0.36}],[{"type":"CriticalDamageBase","value":0.42}],[{"type":"CriticalDamageBase","value":0.48}],[{"type":"CriticalDamageBase","value":0.54}],[{"type":"CriticalDamageBase","value":0.6}]]}