{"id":"23038","skill":"Стремление","desc":"Крит. урон владельца повышается на #1[i]%. Когда владелец выполняет бонус-атаку, он восстанавливает #2[i] ед. энергии и получает статус Предсказание на #3[i] хода. Пока владелец имеет статус Предсказание, крит. урон всех союзников повышается на #4[i]%. В начале боя владелец восстанавливает #5[i] ед. энергии и получает статус Предсказание на #6[i] хода.","params":[[0.36,12,2,0.48,21,2],[0.42,12,2,0.6,21,2],[0.48,12,2,0.72,21,2],[0.54,12,2,0.84,21,2],[0.6,12,2,0.96,21,2]],"properties":[[{"type":"CriticalDamageBase","value":0.36}],[{"type":"CriticalDamageBase","value":0.42}],[{"type":"CriticalDamageBase","value":0.48}],[{"type":"CriticalDamageBase","value":0.54}],[{"type":"CriticalDamageBase","value":0.6}]]}