{"id":"1401103","name":"Paisagem Faminta de Vacua","max_level":1,"desc":"Para cada 1 acúmulo de \"Interpretação\" aplicado a inimigos-alvo, A Herta ganha 1 acúmulo de \"Resposta\" até um máximo de #2[i] acúmulo(s). Ao utilizar a Perícia Suprema, cada acúmulo de \"Resposta\" aumenta o multiplicador de Dano da Perícia Suprema em #1[f1]%.","params":[[0.01,99]],"anchor":"Point08","pre_points":[],"level_up_skills":[],"levels":[{"promotion":6,"level":0,"properties":[],"materials":[{"id":"2","num":160000},{"id":"110203","num":8},{"id":"241","num":1},{"id":"110506","num":1}]}],"icon":"icon/skill/1401_skilltree3.png"}