{"id":"21032","name":"Esculpir la luna y tejer las nubes","rarity":4,"path":"Shaman","desc":"Se había enamorado al instante de aquel recipiente dorado y estaba a punto de comprarlo.\nPero la chica raposiana lo llevó a un lado y susurró:\n\"Es mejor que regrese esta noche, benefactor. Decídase entonces\".\nRegresó al caer la noche.\nQuien abrió la puerta, sonriente, era de nuevo esa chica raposiana.\n\"Sígame, benefactor\".\nUn rayo de luna se reflejó en la base del plato grabado.\nEl artesano había labrado los pétalos con líneas de distintas profundidades, detalles que solo podían percibirse a la luz de la luna.\nPor fin recordó por qué este objeto se llamaba \"esculpir la luna y tejer las nubes\".","icon":"icon/light_cone/21032.png","preview":"image/light_cone_preview/21032.png","portrait":"image/light_cone_portrait/21032.png","ranks":{"id":"21032","skill":"Secreto","desc":"Cuando comienza la batalla y al empezar cada turno del portador, se activa uno de los siguientes efectos al azar (el nuevo efecto será distinto del anterior y lo sustituirá): el ATQ de todos los aliados aumenta en un #1[i]%; el Daño CRIT de todos los aliados aumenta en un #2[i]%; la recuperación de energía de todos los aliados aumenta en un #3[i]%. Estos efectos no se pueden acumular con otros del mismo tipo y se disipan cuando el portador es derrotado.","params":[[0.1,0.12,0.06],[0.125,0.15,0.075],[0.15,0.18,0.09],[0.175,0.21,0.105],[0.2,0.24,0.12]],"properties":[[],[],[],[],[]]},"promotions":{"id":"21032","values":[{"hp":{"base":43.2,"step":6.48},"atk":{"base":21.6,"step":3.24},"def":{"base":15,"step":2.25}},{"hp":{"base":95.04,"step":6.48},"atk":{"base":47.52,"step":3.24},"def":{"base":33,"step":2.25}},{"hp":{"base":164.16,"step":6.48},"atk":{"base":82.08,"step":3.24},"def":{"base":57,"step":2.25}},{"hp":{"base":233.28,"step":6.48},"atk":{"base":116.64,"step":3.24},"def":{"base":81,"step":2.25}},{"hp":{"base":302.4,"step":6.48},"atk":{"base":151.2,"step":3.24},"def":{"base":105,"step":2.25}},{"hp":{"base":371.52,"step":6.48},"atk":{"base":185.76,"step":3.24},"def":{"base":129,"step":2.25}},{"hp":{"base":440.64,"step":6.48},"atk":{"base":220.32,"step":3.24},"def":{"base":153,"step":2.25}}],"materials":[[{"id":"2","num":4000},{"id":"111011","num":5}],[{"id":"2","num":8000},{"id":"110161","num":3},{"id":"111011","num":10}],[{"id":"2","num":16000},{"id":"110162","num":3},{"id":"111012","num":6}],[{"id":"2","num":40000},{"id":"110162","num":6},{"id":"111012","num":9}],[{"id":"2","num":80000},{"id":"110163","num":4},{"id":"111013","num":5}],[{"id":"2","num":160000},{"id":"110163","num":8},{"id":"111013","num":7}],[]]}}