{"id":"150201","name":"Freudiger Kampf mit gefiederten Pfeilen","max_level":10,"element":"Physical","type":"Normal","type_text":"Standardangriff","effect":"Blast","effect_text":"Ausdehnung","simple_desc":"Fügt einem Gegner und angrenzenden Einheiten geringen physischen SCH zu.","desc":"Fügt einem anvisierten Gegner physischen SCH in Höhe von #1[i]% von Yao Guangs ANG zu und fügt gleichzeitig angrenzenden Einheiten physischen SCH in Höhe von #2[i]% von Yao Guangs ANG zu. Erhöht die durch Standardangriffe wiederhergestellte Energie auf 30.","params":[[0.45,0.15],[0.54,0.18],[0.63,0.21],[0.72,0.24],[0.81,0.27],[0.9,0.3],[0.99,0.33],[1.08,0.36],[1.17,0.39],[1.26,0.42]],"icon":"icon/skill/1502_basic_atk.png"}