{"id":"800807","name":"Erweckte Erinnerungen","max_level":1,"element":"","type":"Maze","type_text":"Technik","effect":"Impair","effect_text":"Beeinträchtigung","simple_desc":"Erzeugt eine spezielle Dimension, die alle Gegner in ihr anhält. Nach Kampfeintritt mit Gegnern in dieser Dimension wird die Aktion aller Gegner verzögert und ihnen geringen Eis-SCH zugefügt.","desc":"Erzeugt nach dem Einsatz der Technik für #1[i] Sek. eine spezielle Dimension. Gegner in der Dimension werden in den Status „Zeitstillstand“ versetzt. In diesem Status werden die Aktionen der Gegner angehalten.\nNach Kampfeintritt mit Gegnern im Status Zeitstillstand wird die Aktion aller Gegner um #2[i]% verzögert. Anschließend wird allen Gegner Eis-SCH in Höhe von #3[i]% des ANG {F#der Trailblazerin}{M#des Trailblazers} zugefügt.\nEs kann nur eine von Verbündeten erschaffene Dimension zur gleichen Zeit existieren.","params":[[10,0.5,1]],"icon":"icon/skill/8008_technique.png"}