{"id":"130504","name":"나는 생각한다, 고로 존재한다","max_level":15,"element":"Imaginary","type":"Talent","type_text":"특성","effect":"SingleAttack","effect_text":"단일 공격","simple_desc":"전투 스킬 발동 시 일정 확률로 해당 목표에게 추가 공격을 1회 발동하여 허수 속성 피해를 가한다","desc":"전투 스킬 발동 시 #2[i]%의 고정 확률로 해당 목표에게 추가 공격을 1회 발동하며, Dr. 레이시오 공격력의 #1[i]%만큼 허수 속성 피해를 가한다. 목표가 디버프 효과를 1개 보유할 때마다 추가 공격을 발동할 고정 확률이 #3[i]% 증가한다. 만약 추가 공격 발동 전에 목표가 처치되면 랜덤의 단일 적에게 추가 공격을 발동한다","params":[[1.35,0.4,0.2],[1.485,0.4,0.2],[1.62,0.4,0.2],[1.755,0.4,0.2],[1.89,0.4,0.2],[2.025,0.4,0.2],[2.1938,0.4,0.2],[2.3625,0.4,0.2],[2.5312,0.4,0.2],[2.7,0.4,0.2],[2.835,0.4,0.2],[2.97,0.4,0.2],[3.105,0.4,0.2],[3.24,0.4,0.2],[3.375,0.4,0.2]],"icon":"icon/skill/1305_talent.png"}