{"id":"140707","name":"비명, 죽음을 하사하는 선성","max_level":1,"element":"Quantum","type":"Maze","type_text":"비술","effect":"MazeAttack","effect_text":"","simple_desc":"[아득한 어둠] 상태에 진입하며, 적은 카스토리스에게 직접 다가올 수 없다.\n[아득한 어둠] 상태에서 공격 시 범위 내 모든 적을 전투에 진입시키고, 동시에 기억 정령 죽음의 용을 소환하고 행동 게이지를 100% 증가시킨다. 전투 진입 시, 죽음의 용을 제외한 모든 아군의 HP를 소모한다.\n전투 진입 후 죽음의 용이 소환되지 않을 시 카스토리스는 [새로운 꽃술]을 [새로운 꽃술] 최대치의 30%만큼 회복한다","desc":"비술 사용 후 #3[i]초 동안 [아득한 어둠] 상태에 진입한다. [아득한 어둠] 상태의 적은 카스토리스에게 직접 다가올 수 없다.\n[아득한 어둠] 상태에서 선공하면 범위 내 모든 적을 전투에 진입시키고, 동시에 기억 정령 죽음의 용을 소환하고 행동 게이지를 100% 증가시키며, 경계 [세상을 잊은 저승]을 펼친다. 또한, 죽음의 용은 [새로운 꽃술] 최대치의 #2[i]%만큼 현재 HP를 보유한다. 전투 진입 후, 죽음의 용을 제외한 모든 아군의 현재 HP를 #1[i]% 소모한다.\n전투 진입 후 죽음의 용이 소환되지 않을 시 카스토리스는 [새로운 꽃술]을 [새로운 꽃술] 최대치의 #4[i]%만큼 획득한다","params":[[0.4,0.5,20,0.3]],"icon":"icon/skill/1407_technique.png"}