{"id":"21040","name":"The Day The Cosmos Fell","rarity":4,"path":"Mage","desc":"\"Molten Cheese Tart! You are in charge of disarming the planet's lookouts with your charm!\"\n\"Gray Bean Paste! You will be in charge of breaching the planet's line of defense!\"\n\"Salty Rimeplume! Bring us the head of the planet's leader!\"\n\"My lord, what are you going to do!\"\n\"I shall pretend to be an adorable kitten to befuddle these stupid humans!\"\nThat day, the Cosmos remembered... the terror of being ruled by them.","icon":"icon/light_cone/21040.png","preview":"image/light_cone_preview/21040.png","portrait":"image/light_cone_portrait/21040.png"}