{"id":"110206","name":"Shattering Shambles","rank":6,"desc":"หลังจากใช้ท่าไม้ตาย จะทำให้ศัตรูหนึ่งตัวที่ถูกโจมตีติดสถานะ \"Butterfly Flurry\" เป็นเวลา 1 เทิร์น หลังจากศัตรูเป้าหมายที่ติดสถานะ \"Butterfly Flurry\" ถูกโจมตีแล้ว ศัตรูจะได้รับ DMG ควอนตัมเพิ่มเติม 15% ของ DMG ท่าไม้ตายของ Seele จำนวนหนึ่งครั้ง หากเป้าหมายนั้นถูกกำจัดโดยเป้าหมายอื่นในฝ่ายเราด้วยการใช้ DMG เพิ่มเติมจากสถานะ \"Butterfly Flurry\" พรสวรรค์ของ Seele จะไม่ถูกปล่อย\\nเมื่อ Seele หมดสติ สถานะ \"Butterfly Flurry\" ของศัตรูเป้าหมายจะถูกลบ","materials":[{"id":"11102","num":1}],"level_up_skills":[],"icon":"icon/skill/1102_rank6.png"}