{"id":"100107","name":"Beleza Glacial","max_level":1,"element":"Ice","type":"Maze","type_text":"Técnica","effect":"MazeAttack","effect_text":"","simple_desc":"Ataca o inimigo. Depois de entrar em batalha, existe uma alta chance de infligir Congelamento em um inimigo aleatório.","desc":"Ataca o inimigo imediatamente. Após entrar na batalha, tem #1[i]% de chance-base de causar Congelamento a um inimigo aleatório por #2[i] rodada(s).\nDurante o Congelamento, o inimigo não pode agir e recebe #3[i]% do ATQ de 7 de Março como Dano de Gelo Adicional no início de cada rodada.","params":[[1,1,0.5]],"icon":"icon/skill/1001_technique.png"}