{"id":"110102","name":"Боевая передислокация","max_level":15,"element":"","type":"BPSkill","type_text":"Навык","effect":"Support","effect_text":"Поддержка","simple_desc":"Снимает 1 ослабление с союзника, повышает его урон и заставляет его немедленно выполнить действие.","desc":"Снимает 1 ослабление с союзника и позволяет ему выполнить действие немедленно, а также повышает его урон на #1[i]% на #3[i] ход.\nКогда этот навык используется на самой Броне, она не может совершить действие повторно.","params":[[0.33,0,1,1],[0.363,0,1,1],[0.396,0,1,1],[0.429,0,1,1],[0.462,0,1,1],[0.495,0,1,1],[0.5363,0,1,1],[0.5775,0,1,1],[0.6188,0,1,1],[0.66,0,1,1],[0.693,0,1,1],[0.726,0,1,1],[0.759,0,1,1],[0.792,0,1,1],[0.825,0,1,1]],"icon":"icon/skill/1101_skill.png"}