{"id":"1115","name":"Mặt Nạ Kẻ Ngốc","desc":"Thay thế tất cả Chúc Phúc thành Chúc Phúc ngẫu nhiên, nếu đã cường hóa sẽ được bảo lưu, và có xác suất thay thế thành Chúc Phúc hiếm hơn.","bg_desc":"Mặt nạ của Kẻ Ngốc Đeo Mặt Nạ tượng trưng cho niềm tin đối với \"Vui Vẻ\", đeo mặt nạ trở thành vé vào cổng của kẻ ngốc khi đến quán rượu ở tận cùng thế giới. Chúng nặng và có màu sắc sặc sỡ, nụ cười kiêu ngạo nhưng nét vẽ kín đáo, chờ đợi tất cả những trò đùa hả hê, kèm theo lòng thành kính được Kẻ Ngốc Đeo Mặt Nạ chứng nhận, nhưng có vẻ đều được trộm từ trên thuyền của Kẻ Khóc Thuê.","icon":"icon/curio/1067.png"}