{"id":"3008","name":"Giấy Da Dê Ồn Ào","desc":"Khi vào chiến đấu, toàn phe địch chịu sát thương cố định bằng 30% Giới Hạn HP của mỗi người","bg_desc":"Trong danh sách Vật Thể Lạ của Herta, cấp độ nguy hiểm của tấm Giấy Da Dê này được đánh dấu rất cao. Trước khi lưu lạc đến Trạm Không Gian Herta, nó từng thuộc về một Nhà Sử Học Hư Cấu. Thức ăn của Giấy Da Dê chính là lịch sử của loài người, chiếc lưỡi tham lam của nó khuấy động ý thức tiềm ẩm của tập thể văn minh, khiến nó vỡ tan tành. Herta đã ngụy tạo nên ký ức thế giới hư ảo để nó nuốt vào, nhằm đáp ứng sự tham lam vô cùng tận của nó. Nhưng sẽ có một ngày, tấm Giấy Da Dê này sẽ nhìn ra được mưu kế của thiên tài.","icon":"icon/curio/1008.png"}