{"id":"1223","name":"モゼ","tag":"moze","rarity":4,"path":"Rogue","element":"Thunder","max_sp":120,"ranks":[{"id":"122301","name":"{RUBY_B#りっし}立志{RUBY_E#}","rank":1,"desc":"戦闘に入った後、モゼはEPを20回復する。天賦による付加ダメージを1回発動するたびに、EPを2回復する。","materials":[{"id":"11223","num":1}],"level_up_skills":[],"icon":"icon/skill/1223_rank1.png"},{"id":"122302","name":"{RUBY_B#ちょうばつ}懲罰{RUBY_E#}","rank":2,"desc":"味方が「獲物」状態の敵にダメージを与える時、会心ダメージ+40%。","materials":[{"id":"11223","num":1}],"level_up_skills":[],"icon":"icon/skill/1223_rank2.png"},{"id":"122303","name":"{RUBY_B#ついげき}追撃{RUBY_E#}","rank":3,"desc":"必殺技のLv.+2、最大Lv.15まで。天賦のLv.+2、最大Lv.15まで。","materials":[{"id":"11223","num":1}],"level_up_skills":[{"id":"122303","num":2},{"id":"122304","num":2}],"icon":"icon/skill/1223_skill.png"},{"id":"122304","name":"{RUBY_B#おんみつ}隠密{RUBY_E#}","rank":4,"desc":"必殺技を発動する時、モゼの与ダメージ+30.0%、2ターン継続。","materials":[{"id":"11223","num":1}],"level_up_skills":[],"icon":"icon/skill/1223_rank4.png"},{"id":"122305","name":"{RUBY_B#ぎまん}欺瞞{RUBY_E#}","rank":5,"desc":"戦闘スキルのLv.+2、最大Lv.15まで。通常攻撃のLv.+1、最大Lv.10まで。","materials":[{"id":"11223","num":1}],"level_up_skills":[{"id":"122302","num":2},{"id":"122301","num":1}],"icon":"icon/skill/1223_ultimate.png"},{"id":"122306","name":"{RUBY_B#ちゅうせい}忠誠{RUBY_E#}","rank":6,"desc":"天賦による追加攻撃のダメージ倍率+25%。","materials":[{"id":"11223","num":1}],"level_up_skills":[],"icon":"icon/skill/1223_rank6.png"}],"skills":[{"id":"122301","name":"暗器","max_level":9,"element":"Thunder","type":"Normal","type_text":"通常攻撃","effect":"SingleAttack","effect_text":"単体攻撃","simple_desc":"敵単体に少量の雷属性ダメージを与える。","desc":"指定した敵単体にモゼの攻撃力#1[i]%分の雷属性ダメージを与える。","params":[[0.5],[0.6],[0.7],[0.8],[0.9],[1],[1.1],[1.2],[1.3]],"icon":"icon/skill/1223_basic_atk.png"},{"id":"122302","name":"急襲する迅羽","max_level":15,"element":"Thunder","type":"BPSkill","type_text":"戦闘スキル","effect":"SingleAttack","effect_text":"単体攻撃","simple_desc":"敵単体を「獲物」状態にし、雷属性ダメージを与え、チャージを9獲得する。","desc":"指定した敵単体を「獲物」状態にし、モゼの攻撃力#1[i]%分の雷属性ダメージを与え、チャージを#2[i]獲得する。\nフィールド上に戦闘可能な他の味方キャラがいない時、モゼは戦闘スキルを発動できず、敵の「獲物」状態も解除される。","params":[[0.75,9],[0.825,9],[0.9,9],[0.975,9],[1.05,9],[1.125,9],[1.2188,9],[1.3125,9],[1.4062,9],[1.5,9],[1.575,9],[1.65,9],[1.725,9],[1.8,9],[1.875,9]],"icon":"icon/skill/1223_skill.png"},{"id":"122303","name":"潜む刃、鋭い影","max_level":15,"element":"Thunder","type":"Ultra","type_text":"必殺技","effect":"SingleAttack","effect_text":"単体攻撃","simple_desc":"敵単体に雷属性ダメージを与え、天賦による追加攻撃を発動する。","desc":"指定した敵単体にモゼの攻撃力#1[i]%分の雷属性ダメージを与え、天賦による追加攻撃を行う。この回の追加攻撃を行う前にターゲットが倒された場合、ランダムな敵単体に追加攻撃を行う。","params":[[1.62],[1.728],[1.836],[1.944],[2.052],[2.16],[2.295],[2.43],[2.565],[2.7],[2.808],[2.916],[3.024],[3.132],[3.24]],"icon":"icon/skill/1223_ultimate.png"},{"id":"122304","name":"翼を折りて鋒鋩とす","max_level":15,"element":"Thunder","type":"Talent","type_text":"天賦","effect":"SingleAttack","effect_text":"単体攻撃","simple_desc":"フィールド上に「獲物」状態の敵がいる時、モゼは一時離脱状態に入る。\n味方が「獲物」状態の敵を攻撃した後、モゼはその敵に雷属性付加ダメージを与え、チャージを1消費する。チャージを3消費するたびに、モゼは「獲物」状態の敵に追加攻撃を行い、雷属性ダメージを与える。チャージが0になると、敵の「獲物」状態が解除される。","desc":"フィールド上に「獲物」状態の敵がいる時、モゼは一時離脱状態に入る。\n味方が「獲物」状態の敵を攻撃した後、モゼはその敵に自身の攻撃力#1[i]%分の雷属性付加ダメージを与え、チャージを1消費する。チャージを#2[i]消費するたびに、モゼは「獲物」状態の敵に対して追加攻撃を1回行い、自身の攻撃力#3[i]%分の雷属性ダメージを与える。チャージが0になると敵の「獲物」状態が解除され、追加攻撃発動に必要なチャージ数がリセットされる。なお、天賦による追加攻撃はチャージを消費しない。","params":[[0.15,3,0.8],[0.165,3,0.88],[0.18,3,0.96],[0.195,3,1.04],[0.21,3,1.12],[0.225,3,1.2],[0.2437,3,1.3],[0.2625,3,1.4],[0.2812,3,1.5],[0.3,3,1.6],[0.315,3,1.68],[0.33,3,1.76],[0.345,3,1.84],[0.36,3,1.92],[0.375,3,2]],"icon":"icon/skill/1223_talent.png"},{"id":"122306","name":"攻撃","max_level":1,"element":"Thunder","type":"MazeNormal","type_text":"","effect":"MazeAttack","effect_text":"","simple_desc":"","desc":"敵を攻撃。戦闘に入った後、敵の対応する属性の靭性を削る。","params":[],"icon":"icon/skill/1223_basic_atk.png"},{"id":"122307","name":"見えざる脅威","max_level":1,"element":"","type":"Maze","type_text":"秘技","effect":"Enhance","effect_text":"強化","simple_desc":"ステルス状態に入る。ステルス状態で敵を先制攻撃して戦闘に入った時、与ダメージがアップする。","desc":"秘技を使用した後、#1[i]秒間継続するステルス状態に入る。ステルス状態の間は敵に発見されない。ステルス状態のモゼが敵を先制攻撃して戦闘に入った時、与ダメージ+#2[i]%、#3[i]ターン継続。","params":[[20,0.3,2]],"icon":"icon/skill/1223_technique.png"}],"skill_trees":[{"id":"1223001","name":"","max_level":6,"desc":"","params":[],"anchor":"Point01","pre_points":[],"level_up_skills":[{"id":"122301","num":1}],"levels":[{"promotion":0,"level":0,"properties":[],"materials":[]},{"promotion":2,"level":0,"properties":[],"materials":[{"id":"2","num":4000},{"id":"110191","num":2},{"id":"113011","num":4}]},{"promotion":3,"level":0,"properties":[],"materials":[{"id":"2","num":8000},{"id":"110192","num":2},{"id":"113012","num":2}]},{"promotion":4,"level":0,"properties":[],"materials":[{"id":"2","num":16000},{"id":"110192","num":4},{"id":"113012","num":3}]},{"promotion":5,"level":0,"properties":[],"materials":[{"id":"2","num":36000},{"id":"110193","num":2},{"id":"113013","num":2}]},{"promotion":6,"level":0,"properties":[],"materials":[{"id":"2","num":128000},{"id":"110193","num":6},{"id":"113013","num":3}]}],"icon":"icon/skill/1223_basic_atk.png"},{"id":"1223002","name":"","max_level":10,"desc":"","params":[],"anchor":"Point02","pre_points":[],"level_up_skills":[{"id":"122302","num":1}],"levels":[{"promotion":0,"level":0,"properties":[],"materials":[]},{"promotion":1,"level":0,"properties":[],"materials":[{"id":"2","num":2000},{"id":"113011","num":2}]},{"promotion":2,"level":0,"properties":[],"materials":[{"id":"2","num":4000},{"id":"110191","num":2},{"id":"113011","num":4}]},{"promotion":3,"level":0,"properties":[],"materials":[{"id":"2","num":8000},{"id":"110192","num":2},{"id":"113012","num":2}]},{"promotion":4,"level":0,"properties":[],"materials":[{"id":"2","num":16000},{"id":"110192","num":4},{"id":"113012","num":3}]},{"promotion":4,"level":0,"properties":[],"materials":[{"id":"2","num":24000},{"id":"110192","num":6},{"id":"113012","num":5}]},{"promotion":5,"level":0,"properties":[],"materials":[{"id":"2","num":36000},{"id":"110193","num":2},{"id":"113013","num":2}]},{"promotion":5,"level":0,"properties":[],"materials":[{"id":"2","num":64000},{"id":"110193","num":4},{"id":"110506","num":1},{"id":"113013","num":3}]},{"promotion":6,"level":0,"properties":[],"materials":[{"id":"2","num":128000},{"id":"110193","num":6},{"id":"110506","num":1}]},{"promotion":6,"level":0,"properties":[],"materials":[{"id":"2","num":240000},{"id":"110193","num":11},{"id":"241","num":1},{"id":"110506","num":1}]}],"icon":"icon/skill/1223_skill.png"},{"id":"1223003","name":"","max_level":10,"desc":"","params":[],"anchor":"Point03","pre_points":[],"level_up_skills":[{"id":"122303","num":1}],"levels":[{"promotion":0,"level":0,"properties":[],"materials":[]},{"promotion":1,"level":0,"properties":[],"materials":[{"id":"2","num":2000},{"id":"113011","num":2}]},{"promotion":2,"level":0,"properties":[],"materials":[{"id":"2","num":4000},{"id":"110191","num":2},{"id":"113011","num":4}]},{"promotion":3,"level":0,"properties":[],"materials":[{"id":"2","num":8000},{"id":"110192","num":2},{"id":"113012","num":2}]},{"promotion":4,"level":0,"properties":[],"materials":[{"id":"2","num":16000},{"id":"110192","num":4},{"id":"113012","num":3}]},{"promotion":4,"level":0,"properties":[],"materials":[{"id":"2","num":24000},{"id":"110192","num":6},{"id":"113012","num":5}]},{"promotion":5,"level":0,"properties":[],"materials":[{"id":"2","num":36000},{"id":"110193","num":2},{"id":"113013","num":2}]},{"promotion":5,"level":0,"properties":[],"materials":[{"id":"2","num":64000},{"id":"110193","num":4},{"id":"110506","num":1},{"id":"113013","num":3}]},{"promotion":6,"level":0,"properties":[],"materials":[{"id":"2","num":128000},{"id":"110193","num":6},{"id":"110506","num":1}]},{"promotion":6,"level":0,"properties":[],"materials":[{"id":"2","num":240000},{"id":"110193","num":11},{"id":"241","num":1},{"id":"110506","num":1}]}],"icon":"icon/skill/1223_ultimate.png"},{"id":"1223004","name":"","max_level":10,"desc":"","params":[],"anchor":"Point04","pre_points":[],"level_up_skills":[{"id":"122304","num":1}],"levels":[{"promotion":0,"level":0,"properties":[],"materials":[]},{"promotion":1,"level":0,"properties":[],"materials":[{"id":"2","num":2000},{"id":"113011","num":2}]},{"promotion":2,"level":0,"properties":[],"materials":[{"id":"2","num":4000},{"id":"110191","num":2},{"id":"113011","num":4}]},{"promotion":3,"level":0,"properties":[],"materials":[{"id":"2","num":8000},{"id":"110192","num":2},{"id":"113012","num":2}]},{"promotion":4,"level":0,"properties":[],"materials":[{"id":"2","num":16000},{"id":"110192","num":4},{"id":"113012","num":3}]},{"promotion":4,"level":0,"properties":[],"materials":[{"id":"2","num":24000},{"id":"110192","num":6},{"id":"113012","num":5}]},{"promotion":5,"level":0,"properties":[],"materials":[{"id":"2","num":36000},{"id":"110193","num":2},{"id":"113013","num":2}]},{"promotion":5,"level":0,"properties":[],"materials":[{"id":"2","num":64000},{"id":"110193","num":4},{"id":"110506","num":1},{"id":"113013","num":3}]},{"promotion":6,"level":0,"properties":[],"materials":[{"id":"2","num":128000},{"id":"110193","num":6},{"id":"110506","num":1}]},{"promotion":6,"level":0,"properties":[],"materials":[{"id":"2","num":240000},{"id":"110193","num":11},{"id":"241","num":1},{"id":"110506","num":1}]}],"icon":"icon/skill/1223_talent.png"},{"id":"1223007","name":"","max_level":1,"desc":"","params":[],"anchor":"Point05","pre_points":[],"level_up_skills":[{"id":"122307","num":1}],"levels":[{"promotion":0,"level":0,"properties":[],"materials":[]}],"icon":"icon/skill/1223_technique.png"},{"id":"1223101","name":"{RUBY_B#からすば}烏羽{RUBY_E#}の{RUBY_B#ころも}衣{RUBY_E#}","max_level":1,"desc":"天賦による追加攻撃を行った後、SPを#1[i]回復する。この効果は#2[i]ターン後に再度発動できる。","params":[[1,1]],"anchor":"Point06","pre_points":[],"level_up_skills":[],"levels":[{"promotion":2,"level":0,"properties":[],"materials":[{"id":"2","num":4000},{"id":"110191","num":2},{"id":"110506","num":1}]}],"icon":"icon/skill/1223_skilltree1.png"},{"id":"1223102","name":"{RUBY_B#しの}忍{RUBY_E#}び{RUBY_B#よ}寄{RUBY_E#}る{RUBY_B#あいくち}匕首{RUBY_E#}","max_level":1,"desc":"モゼの一時離脱状態が解除される時、行動順+#1[i]%。各ウェーブ開始時、モゼの行動順+#2[i]%。","params":[[0.2,0.3]],"anchor":"Point07","pre_points":[],"level_up_skills":[],"levels":[{"promotion":4,"level":0,"properties":[],"materials":[{"id":"2","num":16000},{"id":"110192","num":4},{"id":"241","num":1},{"id":"110506","num":1}]}],"icon":"icon/skill/1223_skilltree2.png"},{"id":"1223103","name":"その{RUBY_B#かげ}影{RUBY_E#}、{RUBY_B#ほうけん}宝剣{RUBY_E#}と{RUBY_B#とも}共{RUBY_E#}に{RUBY_B#あ}在{RUBY_E#}り","max_level":1,"desc":"必殺技を発動してダメージを与える時、追加攻撃を行うと見なされる。「獲物」状態の敵が受ける追加攻撃ダメージ+#1[i]%。","params":[[0.25]],"anchor":"Point08","pre_points":[],"level_up_skills":[],"levels":[{"promotion":6,"level":0,"properties":[],"materials":[{"id":"2","num":128000},{"id":"110193","num":6},{"id":"241","num":1},{"id":"110506","num":1}]}],"icon":"icon/skill/1223_skilltree3.png"},{"id":"1223201","name":"会心ダメージ強化","max_level":1,"desc":"","params":[],"anchor":"Point09","pre_points":[],"level_up_skills":[],"levels":[{"promotion":0,"level":1,"properties":[{"type":"CriticalDamageBase","value":0.053}],"materials":[{"id":"2","num":2000},{"id":"113011","num":2}]}],"icon":"icon/property/IconCriticalDamage.png"},{"id":"1223202","name":"攻撃強化","max_level":1,"desc":"","params":[],"anchor":"Point10","pre_points":["1223101"],"level_up_skills":[],"levels":[{"promotion":2,"level":0,"properties":[{"type":"AttackAddedRatio","value":0.04}],"materials":[{"id":"2","num":4000},{"id":"110191","num":2},{"id":"113011","num":4}]}],"icon":"icon/property/IconAttack.png"},{"id":"1223203","name":"会心ダメージ強化","max_level":1,"desc":"","params":[],"anchor":"Point11","pre_points":["1223202"],"level_up_skills":[],"levels":[{"promotion":3,"level":0,"properties":[{"type":"CriticalDamageBase","value":0.053}],"materials":[{"id":"2","num":8000},{"id":"110192","num":2},{"id":"113012","num":2}]}],"icon":"icon/property/IconCriticalDamage.png"},{"id":"1223204","name":"HP強化","max_level":1,"desc":"","params":[],"anchor":"Point12","pre_points":[],"level_up_skills":[],"levels":[{"promotion":3,"level":0,"properties":[{"type":"HPAddedRatio","value":0.04}],"materials":[{"id":"2","num":8000},{"id":"110192","num":2},{"id":"113012","num":2}]}],"icon":"icon/property/IconMaxHP.png"},{"id":"1223205","name":"会心ダメージ強化","max_level":1,"desc":"","params":[],"anchor":"Point13","pre_points":["1223102"],"level_up_skills":[],"levels":[{"promotion":4,"level":0,"properties":[{"type":"CriticalDamageBase","value":0.08}],"materials":[{"id":"2","num":16000},{"id":"110192","num":4},{"id":"113012","num":3}]}],"icon":"icon/property/IconCriticalDamage.png"},{"id":"1223206","name":"攻撃強化","max_level":1,"desc":"","params":[],"anchor":"Point14","pre_points":["1223205"],"level_up_skills":[],"levels":[{"promotion":5,"level":0,"properties":[{"type":"AttackAddedRatio","value":0.06}],"materials":[{"id":"2","num":36000},{"id":"110193","num":2},{"id":"113013","num":2}]}],"icon":"icon/property/IconAttack.png"},{"id":"1223207","name":"会心ダメージ強化","max_level":1,"desc":"","params":[],"anchor":"Point15","pre_points":[],"level_up_skills":[],"levels":[{"promotion":5,"level":0,"properties":[{"type":"CriticalDamageBase","value":0.08}],"materials":[{"id":"2","num":36000},{"id":"110193","num":2},{"id":"113013","num":2}]}],"icon":"icon/property/IconCriticalDamage.png"},{"id":"1223208","name":"HP強化","max_level":1,"desc":"","params":[],"anchor":"Point16","pre_points":["1223103"],"level_up_skills":[],"levels":[{"promotion":6,"level":0,"properties":[{"type":"HPAddedRatio","value":0.06}],"materials":[{"id":"2","num":128000},{"id":"110193","num":6},{"id":"113013","num":6}]}],"icon":"icon/property/IconMaxHP.png"},{"id":"1223209","name":"攻撃強化","max_level":1,"desc":"","params":[],"anchor":"Point17","pre_points":["1223208"],"level_up_skills":[],"levels":[{"promotion":0,"level":75,"properties":[{"type":"AttackAddedRatio","value":0.08}],"materials":[{"id":"2","num":128000},{"id":"110193","num":6},{"id":"113013","num":6}]}],"icon":"icon/property/IconAttack.png"},{"id":"1223210","name":"会心ダメージ強化","max_level":1,"desc":"","params":[],"anchor":"Point18","pre_points":["1223208"],"level_up_skills":[],"levels":[{"promotion":0,"level":80,"properties":[{"type":"CriticalDamageBase","value":0.107}],"materials":[{"id":"2","num":128000},{"id":"110193","num":6},{"id":"113013","num":6}]}],"icon":"icon/property/IconCriticalDamage.png"}],"icon":"icon/character/1223.png","preview":"image/character_preview/1223.png","portrait":"image/character_portrait/1223.png","promotions":{"id":"1223","values":[{"hp":{"base":110.4,"step":5.52},"atk":{"base":81.6,"step":4.08},"def":{"base":48,"step":2.4},"spd":{"base":111,"step":0},"taunt":{"base":75,"step":0},"crit_rate":{"base":0.05,"step":0},"crit_dmg":{"base":0.5,"step":0}},{"hp":{"base":154.56,"step":5.52},"atk":{"base":114.24,"step":4.08},"def":{"base":67.2,"step":2.4},"spd":{"base":111,"step":0},"taunt":{"base":75,"step":0},"crit_rate":{"base":0.05,"step":0},"crit_dmg":{"base":0.5,"step":0}},{"hp":{"base":198.72,"step":5.52},"atk":{"base":146.88,"step":4.08},"def":{"base":86.4,"step":2.4},"spd":{"base":111,"step":0},"taunt":{"base":75,"step":0},"crit_rate":{"base":0.05,"step":0},"crit_dmg":{"base":0.5,"step":0}},{"hp":{"base":242.88,"step":5.52},"atk":{"base":179.52,"step":4.08},"def":{"base":105.6,"step":2.4},"spd":{"base":111,"step":0},"taunt":{"base":75,"step":0},"crit_rate":{"base":0.05,"step":0},"crit_dmg":{"base":0.5,"step":0}},{"hp":{"base":287.04,"step":5.52},"atk":{"base":212.16,"step":4.08},"def":{"base":124.8,"step":2.4},"spd":{"base":111,"step":0},"taunt":{"base":75,"step":0},"crit_rate":{"base":0.05,"step":0},"crit_dmg":{"base":0.5,"step":0}},{"hp":{"base":331.2,"step":5.52},"atk":{"base":244.8,"step":4.08},"def":{"base":144,"step":2.4},"spd":{"base":111,"step":0},"taunt":{"base":75,"step":0},"crit_rate":{"base":0.05,"step":0},"crit_dmg":{"base":0.5,"step":0}},{"hp":{"base":375.36,"step":5.52},"atk":{"base":277.44,"step":4.08},"def":{"base":163.2,"step":2.4},"spd":{"base":111,"step":0},"taunt":{"base":75,"step":0},"crit_rate":{"base":0.05,"step":0},"crit_dmg":{"base":0.5,"step":0}}],"materials":[[{"id":"2","num":3200},{"id":"113011","num":4}],[{"id":"2","num":6400},{"id":"113011","num":8}],[{"id":"2","num":12800},{"id":"113012","num":5},{"id":"110424","num":2}],[{"id":"2","num":32000},{"id":"113012","num":8},{"id":"110424","num":5}],[{"id":"2","num":64000},{"id":"113013","num":5},{"id":"110424","num":15}],[{"id":"2","num":128000},{"id":"113013","num":7},{"id":"110424","num":28}],[]]}}