{"id":"21038","name":"Вдали от огня","rarity":4,"path":"Warrior","desc":"- Посылка получена. Прикрой нас, - донёсся голос из рации.\nОн огляделся: враги продолжали проникать в огромное заброшенное здание сквозь сложную конструкцию, окружая его. Они смыкали кольцо всё плотнее.\n- Держись.\nЧерез короткий миг тишины пространство пронзили чудовищные хлопки от апокалиптических взрывов, взмывающих куда-то в небеса. Над полем боя парили клубы пыли, вызванные взрывной волной, и повсюду распространялся дым и ослепляющий свет, от которого ночь стала ярче дня.\n- Ты не в курсе, они ведь специально рассыпали порох повсюду?\nПолы его плаща раскрылись с лёгким шорохом, будто он только что вернулся с прогулки.\n- Конечно.\n- Пора здесь зажечь. Мне достаточно просто чиркнуть спичкой.","icon":"icon/light_cone/21038.png","preview":"image/light_cone_preview/21038.png","portrait":"image/light_cone_portrait/21038.png"}