{"id":"1117","name":"Geist der Ritter der Schönheit","desc":"Nach Erhalt dieser Kuriosität erhältst du Würfelversuch ×4.","bg_desc":"Die Fraktion, die sich am liebsten mit den Rittern der Schönheit anlegt, sind wahrscheinlich die Maskierten Narren. Die Narren vergnügen sich gerne, indem sie den Glauben der Ritter an die mögliche Rückkehr Idrilas ausnutzen, während die Ritter stets fromm und beharrlich auf dem Weg der Schönheit bleiben. Aus den oben genannten Gründen entwickelten die Trauernden Mimen Empathie für die Ritter und ihren Lebenssinn, und sammelten einen wunderschönen Zahn, der von den Rittern der Schönheit auf der Suche nach ästhetischer Vollkommenheit geopfert wurde.","icon":"icon/curio/1051.png"}